libretro/__init__.py
libretro/_typing.py
libretro/_utils.py
libretro/builder.py
libretro/core.py
libretro/error.py
libretro/h.py
libretro/session.py
libretro/api/__init__.py
libretro/api/_utils.py
libretro/api/audio.py
libretro/api/av.py
libretro/api/camera.py
libretro/api/content.py
libretro/api/disk.py
libretro/api/environment.py
libretro/api/led.py
libretro/api/location.py
libretro/api/log.py
libretro/api/memory.py
libretro/api/message.py
libretro/api/microphone.py
libretro/api/midi.py
libretro/api/netpacket.py
libretro/api/options.py
libretro/api/perf.py
libretro/api/power.py
libretro/api/proc.py
libretro/api/rumble.py
libretro/api/savestate.py
libretro/api/sensor.py
libretro/api/timing.py
libretro/api/user.py
libretro/api/vfs.py
libretro/api/input/__init__.py
libretro/api/input/analog.py
libretro/api/input/device.py
libretro/api/input/joypad.py
libretro/api/input/keyboard.py
libretro/api/input/lightgun.py
libretro/api/input/mouse.py
libretro/api/input/pointer.py
libretro/api/video/__init__.py
libretro/api/video/context.py
libretro/api/video/frame.py
libretro/api/video/negotiate.py
libretro/api/video/render.py
libretro/drivers/__init__.py
libretro/drivers/audio/__init__.py
libretro/drivers/audio/array.py
libretro/drivers/audio/driver.py
libretro/drivers/audio/wave.py
libretro/drivers/camera/__init__.py
libretro/drivers/camera/driver.py
libretro/drivers/camera/generator.py
libretro/drivers/content/__init__.py
libretro/drivers/content/driver.py
libretro/drivers/content/standard.py
libretro/drivers/disk/__init__.py
libretro/drivers/disk/driver.py
libretro/drivers/environment/__init__.py
libretro/drivers/environment/composite.py
libretro/drivers/environment/default.py
libretro/drivers/environment/dict.py
libretro/drivers/environment/driver.py
libretro/drivers/input/__init__.py
libretro/drivers/input/driver.py
libretro/drivers/input/iterable.py
libretro/drivers/led/__init__.py
libretro/drivers/led/dict.py
libretro/drivers/led/driver.py
libretro.py-0.5.0.dist-info/LICENSE
libretro.py-0.5.0.dist-info/METADATA
libretro.py-0.5.0.dist-info/WHEEL
libretro.py-0.5.0.dist-info/top_level.txt
libretro.py-0.5.0.dist-info/RECORD
