Metadata-Version: 2.1
Name: libretro.py
Version: 0.5.0
Summary: A libretro frontend for Python intended for testing cores.
Author-email: Jesse Talavera <jesse@jesse.tg>
Maintainer-email: Jesse Talavera <jesse@jesse.tg>
License: MIT License
Project-URL: Homepage, https://github.com/JesseTG/libretro.py
Project-URL: Issues, https://github.com/JesseTG/libretro.py/issues
Project-URL: Repository, https://github.com/JesseTG/libretro.py
Project-URL: Changelog, https://github.com/JesseTG/libretro.py/blob/master/CHANGELOG.md
Keywords: libretro,retroarch,emulation,testing,retrogaming
Classifier: Development Status :: 3 - Alpha
Classifier: Environment :: Console
Classifier: Environment :: Console :: Framebuffer
Classifier: Intended Audience :: Developers
Classifier: License :: OSI Approved :: MIT License
Classifier: Natural Language :: English
Classifier: Operating System :: MacOS
Classifier: Operating System :: Microsoft :: Windows
Classifier: Operating System :: POSIX
Classifier: Operating System :: POSIX :: Linux
Classifier: Programming Language :: C
Classifier: Programming Language :: Python :: 3.11
Classifier: Programming Language :: Python :: 3.12
Classifier: Topic :: Games/Entertainment
Classifier: Topic :: Software Development :: Libraries :: Python Modules
Classifier: Topic :: Software Development :: Testing
Requires-Python: >=3.11
License-File: LICENSE
Requires-Dist: typing_extensions==4.*; python_version < "3.12"
Provides-Extra: build
Requires-Dist: build==1.2.1; extra == "build"
Requires-Dist: setuptools>=69.1.1; extra == "build"
Requires-Dist: twine==5.0.0; extra == "build"
Requires-Dist: pre-commit==3.7.*; extra == "build"
Provides-Extra: cli
Requires-Dist: typer==0.12.5; extra == "cli"
Provides-Extra: dev
Requires-Dist: bandit==1.7.*; extra == "dev"
Requires-Dist: black==24.*; extra == "dev"
Requires-Dist: flake8==6.*; extra == "dev"
Requires-Dist: isort==5.*; extra == "dev"
Requires-Dist: mypy==1.5.*; extra == "dev"
Requires-Dist: libretro.py[build]; extra == "dev"
Provides-Extra: docs
Requires-Dist: Sphinx==7.*; extra == "docs"
Requires-Dist: sphinx-autobuild==2024.*; extra == "docs"
Requires-Dist: sphinx-copybutton==0.5.2; extra == "docs"
Requires-Dist: furo; extra == "docs"
Provides-Extra: doc
Requires-Dist: libretro.py[docs]; extra == "doc"
Provides-Extra: opengl
Requires-Dist: moderngl[headless]>=5.12; extra == "opengl"
Requires-Dist: PyOpenGL==3.1.*; extra == "opengl"
Provides-Extra: opengl-window
Requires-Dist: moderngl-window==2.4.*; extra == "opengl-window"
Requires-Dist: libretro.py[opengl]; extra == "opengl-window"
Provides-Extra: all
Requires-Dist: libretro.py[build,cli,dev,docs,opengl,opengl-window]; extra == "all"
